xairos_arc/__init__.py
xairos_arc/cli.py
xairos_arc/scan.py
xairos_arc-0.2.0.dist-info/entry_points.txt
xairos_arc-0.2.0.dist-info/WHEEL
xairos_arc-0.2.0.dist-info/METADATA
xairos_arc-0.2.0.dist-info/RECORD
