Metadata-Version: 2.1
Name: xairos-arc
Version: 0.2.0
Summary: 
Author: Benjamin Rottke
Author-email: b.rottke@gmail.com
Requires-Python: >=3.7,<4.0
Classifier: Programming Language :: Python :: 3
Classifier: Programming Language :: Python :: 3.7
Classifier: Programming Language :: Python :: 3.8
Classifier: Programming Language :: Python :: 3.9
Requires-Dist: scapy (>=2.4.4,<3.0.0)
Requires-Dist: typer (>=0.3.2,<0.4.0)
